prompt_optimizers/__init__.py
prompt_optimizers/client.py
prompt_optimizers/constants.py
prompt_optimizers/exceptions.py
prompt_optimizers/models.py
prompt_optimizers/utils.py
prompt_optimizers/endpoints/__init__.py
prompt_optimizers/endpoints/chat.py
prompt_optimizers-0.1.1.dist-info/METADATA
prompt_optimizers-0.1.1.dist-info/WHEEL
prompt_optimizers-0.1.1.dist-info/top_level.txt
prompt_optimizers-0.1.1.dist-info/RECORD
