Metadata-Version: 2.4
Name: prompt-optimizers
Version: 0.1.1
Summary: Advanced LLM prompt optimization toolkit for enterprise applications
Author-email: Prompt Optimizers Team <danielle@prompt-optimizers.com>
License-Expression: MIT
Requires-Python: >=3.8
Requires-Dist: requests>=2.25.0
Provides-Extra: dev
Requires-Dist: pytest>=7.0.0; extra == "dev"
Requires-Dist: pytest-cov>=4.0.0; extra == "dev"
Provides-Extra: testing
Requires-Dist: pytest-asyncio>=0.20.0; extra == "testing"
Requires-Dist: httpx>=0.24.0; extra == "testing"
Requires-Dist: respx>=0.20.0; extra == "testing"
